LICENSE
MANIFEST.in
README.rst
setup.cfg
setup.py
blog/__init__.py
blog/admin.py
blog/apps.py
blog/models.py
blog/serializers.py
blog/urls.py
blog/views.py
blog/management/__init__.py
blog/management/commands/__init__.py
blog/management/commands/wait_for_db.py
blog/migrations/0001_initial.py
blog/migrations/0002_author_user.py
blog/migrations/0003_auto_20200618_1850.py
blog/migrations/__init__.py
blog/tests/__init__.py
blog/tests/test_admin.py
blog/tests/test_api.py
blog/tests/test_commands.py
blog/tests/test_models.py
django_shiroe.egg-info/PKG-INFO
django_shiroe.egg-info/SOURCES.txt
django_shiroe.egg-info/dependency_links.txt
django_shiroe.egg-info/top_level.txt